{
  "parent": "minecraft:recipes/root",
  "rewards": {
    "recipes": [
      "bewitchment:alexandrite_block"
    ]
  },
  "criteria": {
    "has_item": {
      "trigger": "minecraft:inventory_changed",
      "conditions": {
        "items": [
          {
            "item": "bewitchment:gem",
            "count": {
              "min": 9
            },
            "data": 8
          }
        ]
      }
    },
    "has_the_recipe": {
      "trigger": "minecraft:recipe_unlocked",
      "conditions": {
        "recipe": "bewitchment:alexandrite_block"
      }
    }
  },
  "requirements": [
    [
      "has_item",
      "has_the_recipe"
    ]
  ]
}
