{
  "parent": "minecraft:recipes/root",
  "rewards": {
    "recipes": [
      "bewitchment:scarlet_orb_alt_2"
    ]
  },
  "criteria": {
    "has_item": {
      "trigger": "minecraft:inventory_changed",
      "conditions": {
        "items": [
          {
            "type": "forge:ore_dict",
            "ore": "nuggetGold"
          }
        ]
      }
    },
    "has_the_recipe": {
      "trigger": "minecraft:recipe_unlocked",
      "conditions": {
        "recipe": "bewitchment:scarlet_orb_alt_2"
      }
    }
  },
  "requirements": [
    [
      "has_item",
      "has_the_recipe"
    ]
  ]
}
